debug_sensor.py
plot_logs.py
sensor_viewer.py
amsky01-1.0.0.dist-info/licenses/LICENSE
amsky01-1.0.0.dist-info/METADATA
amsky01-1.0.0.dist-info/WHEEL
amsky01-1.0.0.dist-info/entry_points.txt
amsky01-1.0.0.dist-info/top_level.txt
amsky01-1.0.0.dist-info/RECORD
